crossval_ensemble/__init__.py
crossval_ensemble/crossval_pipeline.py
crossval_ensemble/custom_pipeline.py
crossval_ensemble/custom_transformed_target_regressor.py
crossval_ensemble-0.0.1.dist-info/LICENSE
crossval_ensemble-0.0.1.dist-info/METADATA
crossval_ensemble-0.0.1.dist-info/WHEEL
crossval_ensemble-0.0.1.dist-info/top_level.txt
crossval_ensemble-0.0.1.dist-info/RECORD
