Metadata-Version: 2.1
Name: crossval-ensemble
Version: 0.0.1
Summary: A scikit-learn wrapper for CrossValidation Ensembles
Home-page: UNKNOWN
Author: Pierre-Alexis Thoumieu
Author-email: pierre-alexis@liberkeys.com
License: UNKNOWN
Platform: UNKNOWN
Requires-Python: >=3.6
License-File: LICENSE
Requires-Dist: catboost (>=1.2)
Requires-Dist: flake8 (>=6.0.0)
Requires-Dist: ipywidgets (>=8.0.6)
Requires-Dist: lightgbm (>=3.3.5)
Requires-Dist: numpy (>=1.25.0)
Requires-Dist: pandas (>=2.0.3)
Requires-Dist: python-dotenv (>=1.0.0)
Requires-Dist: scikit-learn (>=1.3.0)
Requires-Dist: sklearn-pandas (>=2.2.0)
Requires-Dist: tqdm (>=4.65.0)
Requires-Dist: xgboost (>=1.7.6)
